tiramisu/__init__.py
tiramisu/tiramisu.py
tchappui_tiramisu-0.2.1.dist-info/AUTHORS.rst
tchappui_tiramisu-0.2.1.dist-info/LICENSE
tchappui_tiramisu-0.2.1.dist-info/METADATA
tchappui_tiramisu-0.2.1.dist-info/WHEEL
tchappui_tiramisu-0.2.1.dist-info/top_level.txt
tchappui_tiramisu-0.2.1.dist-info/RECORD
