Metadata-Version: 2.1
Name: tchappui-tiramisu
Version: 0.2.1
Summary: Function to remember how to prepare tiramisu
Home-page: https://github.com/tchappui/tiramisu
Author: Thierry Chappuis
Author-email: tchappui@gmail.com
License: MIT license
Keywords: tiramisu
Platform: UNKNOWN
Classifier: Development Status :: 2 - Pre-Alpha
Classifier: Intended Audience :: Developers
Classifier: License :: OSI Approved :: MIT License
Classifier: Natural Language :: English
Classifier: Programming Language :: Python :: 2
Classifier: Programming Language :: Python :: 2.7
Classifier: Programming Language :: Python :: 3
Classifier: Programming Language :: Python :: 3.4
Classifier: Programming Language :: Python :: 3.5
Classifier: Programming Language :: Python :: 3.6
Classifier: Programming Language :: Python :: 3.7
